{
	"configurations" : 
	[
		{
			"directories" : 
			[
				{
					"build" : ".",
					"minimumCMakeVersion" : 
					{
						"string" : "3.16"
					},
					"projectIndex" : 0,
					"source" : ".",
					"targetIndexes" : 
					[
						0
					]
				}
			],
			"name" : "Debug",
			"projects" : 
			[
				{
					"directoryIndexes" : 
					[
						0
					],
					"name" : "Strategy",
					"targetIndexes" : 
					[
						0
					]
				}
			],
			"targets" : 
			[
				{
					"directoryIndex" : 0,
					"id" : "P5v5ARL::@6890427a1f51a3e7e1df",
					"jsonFile" : "target-P5v5ARL-Debug-4cb739c61268623a6702.json",
					"name" : "P5v5ARL",
					"projectIndex" : 0
				}
			]
		}
	],
	"kind" : "codemodel",
	"paths" : 
	{
		"build" : "D:/Users/ASUS/Desktop/突破重围2v2-C++-demo/out/build/x86-Debug",
		"source" : "D:/Users/ASUS/Desktop/突破重围2v2-C++-demo"
	},
	"version" : 
	{
		"major" : 2,
		"minor" : 0
	}
}
